perform_topsis/102103741.py
Topsis_Akshita_102103741-1.0.0.dist-info/LICENSE
Topsis_Akshita_102103741-1.0.0.dist-info/METADATA
Topsis_Akshita_102103741-1.0.0.dist-info/WHEEL
Topsis_Akshita_102103741-1.0.0.dist-info/entry_points.txt
Topsis_Akshita_102103741-1.0.0.dist-info/top_level.txt
Topsis_Akshita_102103741-1.0.0.dist-info/RECORD
