Metadata-Version: 2.1
Name: Topsis-Akshita-102103741
Version: 1.0.0
Summary: Performs TOPSIS
Home-page: https://github.com/akshita6213/Topsis-Implementation.git
Author: Akshita Gupta
Author-email: akshitapatiala06@gmail.com
License: MIT
Classifier: License :: OSI Approved :: MIT License
Classifier: Programming Language :: Python :: 3.6
Classifier: Programming Language :: Python :: 3.7
Classifier: Programming Language :: Python :: 3.8
License-File: LICENSE
